PyNetMHCpan/NetMHCpan.py
PyNetMHCpan/__init__.py
PyNetMHCpan/pynetmhcpan.config
PyNetMHCpan-0.1.5.dist-info/METADATA
PyNetMHCpan-0.1.5.dist-info/WHEEL
PyNetMHCpan-0.1.5.dist-info/top_level.txt
PyNetMHCpan-0.1.5.dist-info/RECORD
