Metadata-Version: 2.1
Name: PyNetMHCpan
Version: 0.1.5
Summary: A simple tool for using NetMHCpan and NetMHCIIpan using multiple CPUs in a Python environment.
Home-page: https://github.com/kevinkovalchik/PyNetMHCpan
Author: Kevin Kovalchik
Author-email: 
License: MIT
Platform: UNKNOWN
Requires-Python: >=3.7
Requires-Dist: numpy
Requires-Dist: pandas
